build_scripts/version.py
build_scripts/__init__.py
cairotft-0.1.2.dist-info/metadata.json
cairotft-0.1.2.dist-info/RECORD
cairotft-0.1.2.dist-info/METADATA
cairotft-0.1.2.dist-info/top_level.txt
cairotft-0.1.2.dist-info/DESCRIPTION.rst
cairotft-0.1.2.dist-info/WHEEL
cairotft/linuxfb.py
cairotft/svg_image.py
cairotft/RELEASE-VERSION
cairotft/__init__.py
cairotft/transitions.py
cairotft/tft.py
cairotft/widgets/__init__.py
cairotft/widgets/marquee.py
cairotft/widgets/blink_icon.py
cairotft/tests/__init__.py
