Metadata-Version: 2.0
Name: cairotft
Version: 0.1.2
Summary: UI library for small tft screens using cairocffi
Home-page: https://github.com/LinkCareServices/cairotft
Author: Thomas Chiroux - Link Care Services
Author-email: tchiroux (at) linkcareservices.org
License: BSD 3-Clause
Keywords: cairo framebuffer tft python
Platform: UNKNOWN
Classifier: Development Status :: 2 - Pre-Alpha
Classifier: Intended Audience :: Developers
Classifier: License :: OSI Approved :: BSD License
Classifier: Operating System :: POSIX :: Linux
Classifier: Programming Language :: Python
Classifier: Programming Language :: Python :: 3.4
Classifier: Topic :: Multimedia :: Graphics
Classifier: Topic :: Software Development :: Libraries :: Python Modules
Classifier: Topic :: Software Development :: User Interfaces
Requires-Dist: cairocffi
Requires-Dist: cairosvg
